xia_engine_bigquery/__init__.py
xia_engine_bigquery/engine.cpython-311-darwin.so
xia_engine_bigquery/proto.cpython-311-darwin.so
xia_engine_bigquery/schema.cpython-311-darwin.so
xia_engine_bigquery-0.1.15.dist-info/LICENSE.txt
xia_engine_bigquery-0.1.15.dist-info/METADATA
xia_engine_bigquery-0.1.15.dist-info/WHEEL
xia_engine_bigquery-0.1.15.dist-info/top_level.txt
xia_engine_bigquery-0.1.15.dist-info/RECORD
