Metadata-Version: 2.1
Name: xia-engine-bigquery
Version: 0.1.15
Summary: UNKNOWN
Home-page: https://develop.x-i-a.com/docs/xia-engine-bigquery/0.1.15/index.html
Author: X-I-A
Author-email: admin@x-i-a.com
License: UNKNOWN
Platform: UNKNOWN
Requires-Python: >=3.9
License-File: LICENSE.txt
Requires-Dist: protobuf
Requires-Dist: google-cloud-bigquery
Requires-Dist: google-cloud-bigquery-storage
Requires-Dist: xia-engine
Requires-Dist: xia-easy-proto
